kiwigrad/__init__.py
kiwigrad/engine.cpython-39-darwin.so
kiwigrad/engine.py
kiwigrad/graph.py
kiwigrad/layers.py
kiwigrad/neurons.py
kiwigrad/nn.py
kiwigrad/skeleton.py
kiwigrad-0.28.dist-info/LICENSE
kiwigrad-0.28.dist-info/METADATA
kiwigrad-0.28.dist-info/WHEEL
kiwigrad-0.28.dist-info/top_level.txt
kiwigrad-0.28.dist-info/RECORD
