Metadata-Version: 2.1
Name: kiwigrad
Version: 0.28
Summary: Mini deep learning framework
Home-page: https://github.com/marcosalvalaggio/kiwigrad
Author: Marco Salvalaggio
Author-email: mar.salvalaggio@gmail.com
License: MIT
Platform: UNKNOWN
Classifier: Programming Language :: Python :: 3
Classifier: License :: OSI Approved :: MIT License
Classifier: Operating System :: OS Independent
Requires-Python: >=3.6
License-File: LICENSE
Requires-Dist: graphviz
